parsescore_client/__init__.py
parsescore_client/app.py
parsescore_client/config.py
parsescore_client/control.py
parsescore_client/lua_converter.py
parsescore_client-0.19.dist-info/WHEEL
parsescore_client-0.19.dist-info/entry_points.txt
parsescore_client-0.19.dist-info/METADATA
parsescore_client-0.19.dist-info/RECORD
