Metadata-Version: 2.3
Name: parsescore-client
Version: 0.19
Summary: ParseScore - A client for collecting character data and adding it to the WoW addon
Requires-Dist: rich
Requires-Dist: loguru
Requires-Dist: python-dotenv
Requires-Dist: slpp
Requires-Dist: thefuzz>=0.22.1
Requires-Dist: httpx
Requires-Dist: flet[all]>=0.28.3
Requires-Python: >=3.13
